Librarymu/__init__.py
Librarymu/my_class.py
gold33423322/__init__.py
gold33423322/gold.py
gold33423322-2.0.dist-info/LICENSE
gold33423322-2.0.dist-info/METADATA
gold33423322-2.0.dist-info/WHEEL
gold33423322-2.0.dist-info/top_level.txt
gold33423322-2.0.dist-info/RECORD
