Metadata-Version: 2.1
Name: gold33423322
Version: 2.0
Summary: Simple library to calculate golden ratio
Home-page: https://github.com/SabillillahX/pipi.git
Author: SabillillahX
Author-email: <sabillillahxtkj@gmail.com>
License: MIT
Keywords: golden_ratio,golden
Classifier: Development Status :: 1 - Planning
License-File: LICENSE
